onegov.newsletter-0.3.1-py3.6-nspkg.pth
onegov/newsletter/.gitignore
onegov/newsletter/__init__.py
onegov/newsletter/collection.py
onegov/newsletter/errors.py
onegov/newsletter/models.py
onegov/newsletter/upgrade.py
onegov/newsletter/tests/conftest.py
onegov/newsletter/tests/test_collection.py
onegov/newsletter/tests/test_model.py
onegov.newsletter-0.3.1.dist-info/METADATA
onegov.newsletter-0.3.1.dist-info/WHEEL
onegov.newsletter-0.3.1.dist-info/entry_points.txt
onegov.newsletter-0.3.1.dist-info/namespace_packages.txt
onegov.newsletter-0.3.1.dist-info/top_level.txt
onegov.newsletter-0.3.1.dist-info/RECORD
