Metadata-Version: 2.1
Name: onegov.newsletter
Version: 0.3.1
Summary: Newsletters for OneGov Cloud.
Home-page: http://github.com/OneGov/onegov.newsletter
Author: Seantis GmbH
Author-email: info@seantis.ch
License: GPLv2
Platform: any
Classifier: Intended Audience :: Developers
Classifier: Programming Language :: Python :: 3 :: Only
Classifier: Programming Language :: Python :: 3.6
Classifier: Programming Language :: Python :: 3.7
Classifier: Topic :: Software Development :: Libraries :: Python Modules
Classifier: License :: OSI Approved :: GNU General Public License v2 (GPLv2)
Requires-Python: >=3.6
Requires-Dist: onegov.core (>=0.4.0)
Requires-Dist: onegov.search
Requires-Dist: sedate
Requires-Dist: validate-email
Provides-Extra: test
Requires-Dist: coverage ; extra == 'test'
Requires-Dist: onegov-testing ; extra == 'test'
Requires-Dist: pytest ; extra == 'test'
